{
  "text": [
    {
      "text": "OUR STRENGTHS",
      "color": "omega",
      "variant": "h6"
    },
    {
      "text": "What Makes Us Different",
      "variant": "h2"
    }
  ],
  "collection": [
    {
      "text": [
        {
          "text": "Turn curiosity into sales",
          "variant": "h5"
        },
        {
          "text": "Craft a unique marketing campaign that ‘gels’ with your ideal customer and turns their curiosity into bona-fide sales. "
        }
      ],
      "images": [
        {
          "src": "../../../assets/flexiblocks/homepage/marketing/curiosity.png",
          "alt": "curiosity",
          "width": "50px",
          "height": "50px"
        }
      ]
    },
    {
      "text": [
        {
          "text": "Driven by data",
          "variant": "h5"
        },
        {
          "text": "Takeout guesswork. Make informed choices about your digital marketing strategy with privacy-centric first-party data solutions."
        }
      ],
      "images": [
        {
          "src": "../../../assets/flexiblocks/homepage/marketing/driven.png",
          "alt": "driven",
          "width": "100px"
        }
      ]
    },
    {
      "text": [
        {
          "text": "Trusted support network",
          "variant": "h5"
        },
        {
          "text": "You are guided every step of the way. Our focus on maintaining a friendly rapport and keeping things transparent means you can relax knowing you are in good hands. "
        }
      ],
      "images": [
        {
          "src": "../../../assets/flexiblocks/homepage/marketing/trusted.png",
          "alt": "trusted"
        }
      ]
    }
  ]
}
